Metadata-Version: 1.0
Name: botany-connectfour
Version: 0.1.1
Summary: Botany connectfour
Home-page: http://github.com/inglesp/botany
Author: Peter Inglesby
Author-email: peter.inglesby@gmail.com
License: License :: OSI Approved :: MIT License
Platform: UNKNOWN
